{
    "DocDate": "2024-12-10",
    "DocDueDate": "2024-12-13",
    "TaxDate": "2024-12-10",
    "CardCode": "5936687C",
    "PaymentGroupCode": -1,
    "SalesPersonCode": 22,
    "TransportationCode": 1,
    "U_LED_TIPVTA": 1,
    "U_LED_TIPDOC": "RESE",
    "U_LED_FORENV": 1,
    "DocumentLines": [
        {
            "LineNum": 0,
            "ItemCode": "A10002075",
            "Quantity": 1,
            "ShipDate": "2024-12-13",
            "DiscountPercent": null,
            "WarehouseCode": "GR",
            "CostingCode": "LC",
            "ShippingMethod": 2,
            "COGSCostingCode": "LC",
            "CostingCode2": "AV",
            "COGSCostingCode2": "AV"
        },
        {
            "LineNum": 1,
            "ItemCode": "A10002075",
            "Quantity": 1,
            "ShipDate": "2024-12-13",
            "DiscountPercent": null,
            "WarehouseCode": "GR",
            "CostingCode": "LC",
            "ShippingMethod": 2,
            "COGSCostingCode": "LC",
            "CostingCode2": "AV",
            "COGSCostingCode2": "AV"
        }
    ]
}'